infer_schema.py
infer_schema-0.1.dist-info/entry_points.txt
infer_schema-0.1.dist-info/LICENSE
infer_schema-0.1.dist-info/WHEEL
infer_schema-0.1.dist-info/METADATA
infer_schema-0.1.dist-info/RECORD
