Metadata-Version: 2.1
Name: infer-schema
Version: 0.1
Summary: Infer JSON schema from CSV file
Author-email: Abhishek Dasgupta <abhidg@trenozoic.net>
Requires-Python: >=3.8
Classifier: License :: OSI Approved :: MIT License
Classifier: Development Status :: 4 - Beta
Classifier: Environment :: Console
Classifier: Programming Language :: Python :: 3
Classifier: Topic :: File Formats :: JSON :: JSON Schema
Requires-Dist: fastjsonschema==2.19.0 ; extra == "test"
Requires-Dist: coverage[toml] ; extra == "test"
Project-URL: Home, https://github.com/abhidg/infer-schema
Provides-Extra: test
